MANIFEST.in
README.md
__init__.py
question2.py
setup.py
SLJustin.egg-info/PKG-INFO
SLJustin.egg-info/SOURCES.txt
SLJustin.egg-info/dependency_links.txt
SLJustin.egg-info/requires.txt
SLJustin.egg-info/top_level.txt