Metadata-Version: 1.1
Name: SLJustin
Version: 0.1
Summary:  Answer test questions about ML ! 
Home-page: https://github.com/javatechy/dokr
Author: Justin Aguenier
Author-email: justin.aguenier@ensae.fr
License: UNKNOWN
Platform: UNKNOWN
Classifier: Programming Language :: Python :: 3
Classifier: License :: OSI Approved :: MIT License
